abstract_audio/__init__.py
abstract_audio/abstract_audio.py
abstract_audio/speech_to_text_gui.py
abstract_audio/audio_player/__init__.py
abstract_audio/audio_player/abstractaudioplayer.py
abstract_audio/audio_player/audioplayer_linux.py
abstract_audio/audio_player/audioplayer_macos.py
abstract_audio/audio_player/audioplayer_windows.py
audio_player/__init__.py
audio_player/abstractaudioplayer.py
audio_player/audioplayer_linux.py
audio_player/audioplayer_macos.py
audio_player/audioplayer_windows.py
abstract_audio-0.0.1.1.dist-info/METADATA
abstract_audio-0.0.1.1.dist-info/WHEEL
abstract_audio-0.0.1.1.dist-info/top_level.txt
abstract_audio-0.0.1.1.dist-info/RECORD
